alignscore/__init__.py
alignscore/alignscore.py
alignscore/dataloader.py
alignscore/inference.py
alignscore/model.py
alignscore_speedofmagic-0.1.4.dist-info/METADATA
alignscore_speedofmagic-0.1.4.dist-info/WHEEL
alignscore_speedofmagic-0.1.4.dist-info/licenses/LICENSE
alignscore_speedofmagic-0.1.4.dist-info/RECORD
