Metadata-Version: 2.4
Name: alignscore-SpeedOfMagic
Version: 0.1.4
Summary: An automatic factual consistency evaluation metric based on a unifined alignment function
Project-URL: Homepage, https://github.com/yuh-zha/AlignScore
Project-URL: Bug Tracker, https://github.com/yuh-zha/AlignScore/issues
Author-email: Yuheng Zha <yzha@ucsd.edu>, Yichi Yang <yiy067@ucsd.edu>, Ruichen Li <rul014@ucsd.edu>, Zhiting Hu <zhh019@ucsd.edu>
License-File: LICENSE
Classifier: License :: OSI Approved :: MIT License
Classifier: Operating System :: OS Independent
Classifier: Programming Language :: Python :: 3
Classifier: Topic :: Scientific/Engineering :: Artificial Intelligence
Requires-Python: >=3.8
Requires-Dist: datasets>=2.3.2
Requires-Dist: jsonlines<3,>=2.0.0
Requires-Dist: nltk<4,>=3.7
Requires-Dist: numpy<2,>=1.23.1
Requires-Dist: protobuf<=3.20.3
Requires-Dist: pytorch-lightning>=1.7.7
Requires-Dist: scikit-learn<2,>=1.1.2
Requires-Dist: scipy<2,>=1.8.1
Requires-Dist: spacy<4,>=3.4.0
Requires-Dist: tensorboard<3,>=2.12.0
Requires-Dist: torch>=1.12.1
Requires-Dist: tqdm<5,>=4.64.0
Requires-Dist: transformers<5,>=4.20.1
